{
  "@type": "dcat:Resource",
  "properties": {
    "dcterms:title": "Mitsubishi Electric Delta Robot System for Plastics Packing",
    "dcterms:type": "robotic system",
    "dcterms:publisher": "Mitsubishi Electric Corporation",
    "dcterms:license": "https://www.mitsubishielectric.com/legal/terms-of-use",
    "dcterms:identifier": "ME-DELTA-PACK-PLASTICS-001",
    "dcterms:description": "High-speed delta robot system designed for automated packing applications in plastics processing industries, featuring precision handling, vision integration, and hygienic design suitable for manufacturing environments.",
    "dcat:version": "2.1.3",
    "dcat:keyword": [
      "delta robot",
      "packing automation",
      "plastics processing",
      "Mitsubishi Electric",
      "industrial robotics",
      "high-speed picking"
    ],
    "dcat:contactPoint": "https://www.mitsubishielectric.com/fa/contact/",
    "rodeos:coreType": "Component"
  },
  "child": {
    "@type": "rodeos:Component",
    "properties": {
      "rodeos:componentType": "hardwareComponent",
      "rodeos:modelParameters": {
        "@type": "schema:quantitativeValue",
        "value": 3.5,
        "unitCode": "kg",
        "minValue": 2.0,
        "maxValue": 5.0
      },
      "rodeos:framework": "MELFA Smart Plus"
    },
    "child": {
      "@type": "rodeos:hardwareComponent",
      "properties": {
        "rodeos:manufacturer": "Mitsubishi Electric",
        "rodeos:hardwareAssetType": "delta"
      },
      "child": {
        "@type": "rodeos:roboter",
        "properties": {
          "rodeos:payload": 3.0,
          "rodeos:maxVelocity": 5.5,
          "rodeos:DOF": 6,
          "rodeos:operatingVoltage": 200.0,
          "rodeos:interface": "EtherCAT",
          "rodeos:reach": 850.0,
          "rodeos:accuracy": 0.05,
          "rodeos:minVelocity": 0.1
        },
        "child": {
          "@type": "rodeos:stationaryRobot",
          "properties": {
            "rodeos:mounting": "Floor-mounted",
            "rodeos:positionAccuracy": 0.05,
            "rodeos:repeatability": 0.02,
            "rodeos:isCobot": false,
            "rodeos:workspaceVolume": 0.785,
            "rodeos:pedestal": true,
            "rodeos:kinematicModel": "Parallel kinematic structure"
          },
          "child": {
            "@type": "rodeos:parallelRobot",
            "properties": {
              "rodeos:platformSize": 0.1,
              "rodeos:stiffness": 1.0
            },
            "child": {
              "@type": "rodeos:delta",
              "properties": {
                "rodeos:aasSubmodel": "https://example.com/aas/submodels/delta-robot-packaging",
                "rodeos:pickRateMax": 120.5,
                "rodeos:workspaceShape": "rodeos:hemispherical"
              }
            }
          }
        }
      }
    }
  }
}